rrule34/__init__.py
rrule34/formatting.py
rrule34/tests/__init__.py
rrule34/tests/test_formatting_en.py
rrule34/tests/test_formatting_fr.py
rrule34-1.0.0.dist-info/DESCRIPTION.rst
rrule34-1.0.0.dist-info/METADATA
rrule34-1.0.0.dist-info/RECORD
rrule34-1.0.0.dist-info/WHEEL
rrule34-1.0.0.dist-info/metadata.json
rrule34-1.0.0.dist-info/top_level.txt
